beautifultable/__init__.py
beautifultable/__version__.py
beautifultable/ansi.py
beautifultable/base.py
beautifultable/beautifultable.py
beautifultable/compat.py
beautifultable/enums.py
beautifultable/helpers.py
beautifultable/meta.py
beautifultable/styles.py
beautifultable/utils.py
beautifultable-1.1.0.dist-info/LICENSE.txt
beautifultable-1.1.0.dist-info/METADATA
beautifultable-1.1.0.dist-info/WHEEL
beautifultable-1.1.0.dist-info/top_level.txt
beautifultable-1.1.0.dist-info/RECORD
