Metadata-Version: 2.1
Name: beautifultable
Version: 1.1.0
Summary: Print text tables for terminals
Home-page: https://github.com/pri22296/beautifultable
Download-URL: https://github.com/pri22296/beautifultable/tarball/1.1.0
Author: Priyam Singh
Author-email: priyamsingh.22296@gmail.com
License: MIT
Keywords: table terminal ascii
Platform: UNKNOWN
Classifier: Development Status :: 4 - Beta
Classifier: Environment :: Console
Classifier: Intended Audience :: Developers
Classifier: License :: OSI Approved :: MIT License
Classifier: Programming Language :: Python
Classifier: Programming Language :: Python :: 3.7
Classifier: Programming Language :: Python :: 3.8
Classifier: Programming Language :: Python :: 3.9
Classifier: Programming Language :: Python :: 3.10
Classifier: Programming Language :: Python :: Implementation :: CPython
Classifier: Programming Language :: Python :: Implementation :: PyPy
Classifier: Topic :: Printing
Classifier: Topic :: Text Processing
Provides-Extra: dev
Provides-Extra: all
License-File: LICENSE.txt
